{
  "id": "Ac1Ca1Ni2P2",
  "uri": "material://Ac1Ca1Ni2P2",
  "composition": {
    "formula": "Ac1Ca1Ni2P2",
    "elements": {
      "Ac": 1,
      "Ca": 1,
      "Ni": 2,
      "P": 2
    },
    "reduced_formula": "CaAc(NiP)2",
    "element_list": [
      "P",
      "Ca",
      "Ni",
      "Ac"
    ]
  },
  "recipe": {
    "materials": {
      "list": [],
      "raw_text": "- Calcium (Ca): 10.8 g  \n - Nickel (Ni): 43.2 g  \n - Phosphorus (P): 9.6 g  \n - Aluminum (Al): 6.2 g"
    },
    "sourcing": {
      "instructions": "- Calcium: Obtain from a chemical supply store or online suppliers specializing in metals.  \n - Nickel: Available from metal suppliers or online marketplaces.  \n - Phosphorus: Purchase from chemical suppliers or agricultural stores.  \n - Aluminum: Source from local hardware stores or metal fabricators.",
      "steps": [
        "- Calcium: Obtain from a chemical supply store or online suppliers specializing in metals.",
        "- Nickel: Available from metal suppliers or online marketplaces.",
        "- Phosphorus: Purchase from chemical suppliers or agricultural stores.",
        "- Aluminum: Source from local hardware stores or metal fabricators."
      ]
    },
    "preparation": {
      "steps": [
        "1. Measure out 10.8 g of Calcium.",
        "2. Measure out 43.2 g of Nickel.",
        "3. Measure out 9.6 g of Phosphorus.",
        "4. Measure out 6.2 g of Aluminum.",
        "5. In a clean, dry mixing container, combine all ingredients thoroughly using a spatula or mixing rod to ensure even distribution."
      ],
      "raw_text": "1. Measure out 10.8 g of Calcium.  \n 2. Measure out 43.2 g of Nickel.  \n 3. Measure out 9.6 g of Phosphorus.  \n 4. Measure out 6.2 g of Aluminum.  \n 5. In a clean, dry mixing container, combine all ingredients thoroughly using a spatula or mixing rod to ensure even distribution."
    },
    "heating": {
      "temperature_celsius": 1200,
      "duration_hours": 2,
      "steps": [
        "1. Transfer the mixed materials into a crucible suitable for high-temperature applications.",
        "2. Place the crucible in a furnace and heat to 1200°C.",
        "3. Maintain this temperature for 2 hours to ensure complete reaction and formation of the desired compound."
      ],
      "raw_text": "1. Transfer the mixed materials into a crucible suitable for high-temperature applications.  \n 2. Place the crucible in a furnace and heat to 1200°C.  \n 3. Maintain this temperature for 2 hours to ensure complete reaction and formation of the desired compound."
    },
    "cooling": {
      "cooling_time_hours": 6,
      "method": "natural",
      "steps": [
        "1. After the heating duration, turn off the furnace and allow the crucible to cool naturally to room temperature, which may take approximately 4-6 hours.",
        "2. Do not open the furnace until it has cooled completely to prevent thermal shock."
      ],
      "raw_text": "1. After the heating duration, turn off the furnace and allow the crucible to cool naturally to room temperature, which may take approximately 4-6 hours.  \n 2. Do not open the furnace until it has cooled completely to prevent thermal shock."
    },
    "post_processing": {
      "steps": [
        "1. Once cooled, carefully remove the solid sample from the crucible.",
        "2. Use a diamond file or sandpaper to smooth out any rough edges and achieve the desired finish.",
        "3. Optionally, seal the surface with a protective coating to enhance durability and prevent oxidation if necessary."
      ],
      "raw_text": "1. Once cooled, carefully remove the solid sample from the crucible.  \n 2. Use a diamond file or sandpaper to smooth out any rough edges and achieve the desired finish.  \n 3. Optionally, seal the surface with a protective coating to enhance durability and prevent oxidation if necessary."
    }
  },
  "properties": {
    "structure": {
      "nsites": 6,
      "volume": 1156927.0,
      "density": 64074.0,
      "crystal_system": "trigonal",
      "space_group": "P-3m1",
      "space_group_number": 164,
      "point_group": "-3m",
      "dimensionality": null
    },
    "energetics": {
      "corrected_energy": -344367.0,
      "formation_energy_per_atom": -9872.0,
      "decomposition_energy_per_atom": -2777.0,
      "decomposition_energy_all": 0.0,
      "decomposition_energy_relative": -35.0,
      "decomposition_energy_mp": -2777.0,
      "decomposition_energy_mp_oqmd": -342.0
    },
    "electronic": {
      "bandgap": null,
      "bandgap_type": "semiconductor"
    },
    "metadata": {
      "material_id": "6bfb071bd5",
      "is_train": false
    }
  },
  "metadata": {
    "source": "Acadia Nanoforge Database",
    "data_version": "1.0",
    "created_at": "2025-10-30T15:13:36.948327Z",
    "mcp_version": "2024-11-05",
    "access_patterns": [
      "materials/Ac1Ca1Ni2P2.json",
      "material://Ac1Ca1Ni2P2"
    ]
  }
}