{
  "id": "Al2Cd1Mg3Tb3",
  "uri": "material://Al2Cd1Mg3Tb3",
  "composition": {
    "formula": "Al2Cd1Mg3Tb3",
    "elements": {
      "Al": 2,
      "Cd": 1,
      "Mg": 3,
      "Tb": 3
    },
    "reduced_formula": "Tb3Mg3Al2Cd",
    "element_list": [
      "Mg",
      "Al",
      "Cd",
      "Tb"
    ]
  },
  "recipe": {
    "materials": {
      "list": [],
      "raw_text": "Aluminum (Al): 24.0 g \n Cadmium (Cd): 2.0 g \n Magnesium (Mg): 6.0 g \n Terbium (Tb): 18.0 g \n Total Weight: 50.0 g"
    },
    "sourcing": {
      "instructions": "Aluminum: Local metal supply store or online metal suppliers. \n Cadmium: Chemical supply companies specializing in rare metals. \n Magnesium: Metal supply stores or online. \n Terbium: Specialty chemical suppliers or online marketplaces.",
      "steps": [
        "Aluminum: Local metal supply store or online metal suppliers.",
        "Cadmium: Chemical supply companies specializing in rare metals.",
        "Magnesium: Metal supply stores or online.",
        "Terbium: Specialty chemical suppliers or online marketplaces."
      ]
    },
    "preparation": {
      "steps": [
        "1. Weigh each metal accurately using a precision scale.",
        "2. In a clean, dry container, combine 24.0 g of Aluminum, 2.0 g of Cadmium, 6.0 g of Magnesium, and 18.0 g of Terbium.",
        "3. Stir the mixture thoroughly to ensure an even distribution of metals."
      ],
      "raw_text": "1. Weigh each metal accurately using a precision scale. \n 2. In a clean, dry container, combine 24.0 g of Aluminum, 2.0 g of Cadmium, 6.0 g of Magnesium, and 18.0 g of Terbium. \n 3. Stir the mixture thoroughly to ensure an even distribution of metals."
    },
    "heating": {
      "temperature_celsius": 600,
      "duration_hours": 1,
      "steps": [
        "1. Transfer the mixed materials into a crucible.",
        "2. Place the crucible in a furnace set to 600 째C.",
        "3. Maintain this temperature for 1 hour to ensure complete melting and homogenization of the alloy."
      ],
      "raw_text": "1. Transfer the mixed materials into a crucible. \n 2. Place the crucible in a furnace set to 600 째C. \n 3. Maintain this temperature for 1 hour to ensure complete melting and homogenization of the alloy."
    },
    "cooling": {
      "cooling_time_hours": 1,
      "method": "natural",
      "steps": [
        "1. After 1 hour, turn off the furnace and allow the crucible to cool slowly to room temperature (approximately 25 째C).",
        "2. This cooling process should take about 2 hours to avoid any thermal shock to the material."
      ],
      "raw_text": "1. After 1 hour, turn off the furnace and allow the crucible to cool slowly to room temperature (approximately 25 째C). \n 2. This cooling process should take about 2 hours to avoid any thermal shock to the material."
    },
    "post_processing": {
      "steps": [
        "1. Once cooled, carefully remove the solid sample from the crucible.",
        "2. Use fine-grit sandpaper to smooth any rough edges and achieve a uniform surface finish.",
        "3. Optionally, apply a clear sealant to protect the surface from oxidation or corrosion."
      ],
      "raw_text": "1. Once cooled, carefully remove the solid sample from the crucible. \n 2. Use fine-grit sandpaper to smooth any rough edges and achieve a uniform surface finish. \n 3. Optionally, apply a clear sealant to protect the surface from oxidation or corrosion."
    }
  },
  "properties": {
    "structure": {
      "nsites": 9,
      "volume": 2193461.0,
      "density": 54209.0,
      "crystal_system": "hexagonal",
      "space_group": "P-62m",
      "space_group_number": 189,
      "point_group": "-6m2",
      "dimensionality": "3D"
    },
    "energetics": {
      "corrected_energy": -296517.0,
      "formation_energy_per_atom": -2815.0,
      "decomposition_energy_per_atom": -16.0,
      "decomposition_energy_all": 0.0,
      "decomposition_energy_relative": 0.0,
      "decomposition_energy_mp": -15.0,
      "decomposition_energy_mp_oqmd": 0.0
    },
    "electronic": {
      "bandgap": 0.0226,
      "bandgap_type": "semiconductor"
    },
    "metadata": {
      "material_id": "2a91bbbc78",
      "is_train": true
    }
  },
  "metadata": {
    "source": "Acadia Nanoforge Database",
    "data_version": "1.0",
    "created_at": "2025-10-30T15:12:11.887905Z",
    "mcp_version": "2024-11-05",
    "access_patterns": [
      "materials/Al2Cd1Mg3Tb3.json",
      "material://Al2Cd1Mg3Tb3"
    ]
  }
}