{
  "id": "Al6Cu1Tc1Zr4",
  "uri": "material://Al6Cu1Tc1Zr4",
  "composition": {
    "formula": "Al6Cu1Tc1Zr4",
    "elements": {
      "Al": 6,
      "Cu": 1,
      "Tc": 1,
      "Zr": 4
    },
    "reduced_formula": "Zr4Al6CuTc",
    "element_list": [
      "Al",
      "Cu",
      "Zr",
      "Tc"
    ]
  },
  "recipe": {
    "materials": {
      "list": [],
      "raw_text": "- Aluminum (Al): 600 g  \n - Copper (Cu): 100 g  \n - Technetium (Tc): 100 g \n - Zirconium (Zr): 400 g"
    },
    "sourcing": {
      "instructions": "- Aluminum: Local metal supplier or online metal retailer. \n - Copper: Electrical supply stores or metal suppliers. \n - Technetium: Specialized nuclear material suppliers (may require licensing). \n - Zirconium: Metal suppliers or online retailers that deal in rare metals.",
      "steps": [
        "- Aluminum: Local metal supplier or online metal retailer.",
        "- Copper: Electrical supply stores or metal suppliers.",
        "- Technetium: Specialized nuclear material suppliers (may require licensing).",
        "- Zirconium: Metal suppliers or online retailers that deal in rare metals."
      ]
    },
    "preparation": {
      "steps": [
        "1. Measure out 600 g of aluminum using a digital scale.",
        "2. Measure 100 g of copper and 100 g of technetium using the same scale.",
        "3. Measure 400 g of zirconium.",
        "4. Combine all measured materials in a clean, dry mixing container.",
        "5. Use a mechanical mixer to ensure a homogenous mixture for at least 10 minutes."
      ],
      "raw_text": "1. Measure out 600 g of aluminum using a digital scale. \n 2. Measure 100 g of copper and 100 g of technetium using the same scale. \n 3. Measure 400 g of zirconium. \n 4. Combine all measured materials in a clean, dry mixing container. \n 5. Use a mechanical mixer to ensure a homogenous mixture for at least 10 minutes."
    },
    "heating": {
      "temperature_celsius": 750,
      "duration_hours": 2,
      "steps": [
        "1. Transfer the mixture into a crucible.",
        "2. Heat the crucible in a furnace to a temperature of 750°C.",
        "3. Maintain this temperature for 2 hours to allow for proper alloy formation."
      ],
      "raw_text": "1. Transfer the mixture into a crucible. \n 2. Heat the crucible in a furnace to a temperature of 750°C. \n 3. Maintain this temperature for 2 hours to allow for proper alloy formation."
    },
    "cooling": {
      "cooling_time_hours": 6,
      "method": "natural",
      "steps": [
        "1. Turn off the furnace and allow the crucible to cool naturally to room temperature.",
        "2. This process should take approximately 4-6 hours. Avoid forced cooling to prevent cracking."
      ],
      "raw_text": "1. Turn off the furnace and allow the crucible to cool naturally to room temperature. \n 2. This process should take approximately 4-6 hours. Avoid forced cooling to prevent cracking."
    },
    "post_processing": {
      "steps": [
        "1. Once cooled, carefully remove the solid sample from the crucible.",
        "2. If necessary, grind the edges to achieve desired dimensions (3 inches x 2 inches x 7 inches) using a metal grinder or sanding tool.",
        "3. Optionally, apply a sealant to improve surface finish and protect the alloy."
      ],
      "raw_text": "1. Once cooled, carefully remove the solid sample from the crucible. \n 2. If necessary, grind the edges to achieve desired dimensions (3 inches x 2 inches x 7 inches) using a metal grinder or sanding tool. \n 3. Optionally, apply a sealant to improve surface finish and protect the alloy."
    }
  },
  "properties": {
    "structure": {
      "nsites": 12,
      "volume": 2075259.0,
      "density": 55078.0,
      "crystal_system": "trigonal",
      "space_group": "P-3m1",
      "space_group_number": 164,
      "point_group": "-3m",
      "dimensionality": "3D"
    },
    "energetics": {
      "corrected_energy": -774363.0,
      "formation_energy_per_atom": -526.0,
      "decomposition_energy_per_atom": -472.0,
      "decomposition_energy_all": 0.0,
      "decomposition_energy_relative": -19.0,
      "decomposition_energy_mp": -471.0,
      "decomposition_energy_mp_oqmd": -23.0
    },
    "electronic": {
      "bandgap": 0.0037,
      "bandgap_type": "semiconductor"
    },
    "metadata": {
      "material_id": "f877171a23",
      "is_train": true
    }
  },
  "metadata": {
    "source": "Acadia Nanoforge Database",
    "data_version": "1.0",
    "created_at": "2025-10-30T15:15:32.452661Z",
    "mcp_version": "2024-11-05",
    "access_patterns": [
      "materials/Al6Cu1Tc1Zr4.json",
      "material://Al6Cu1Tc1Zr4"
    ]
  }
}