{
  "id": "As10Mn10Na1Sr4",
  "uri": "material://As10Mn10Na1Sr4",
  "composition": {
    "formula": "As10Mn10Na1Sr4",
    "elements": {
      "As": 10,
      "Mn": 10,
      "Na": 1,
      "Sr": 4
    },
    "reduced_formula": "NaSr4(MnAs)10",
    "element_list": [
      "Na",
      "Mn",
      "As",
      "Sr"
    ]
  },
  "recipe": {
    "materials": {
      "list": [],
      "raw_text": "**As:** 187.5 g\n**Mn:** 187.5 g\n**Na:** 7.5 g\n**Sr:** 300 g"
    },
    "sourcing": {
      "instructions": "**As:** Purchase from a chemical supplier or online platform (ensure purity).\n**Mn:** Obtain from a metal supplier, such as a local hardware store or online.\n**Na:** Buy sodium metal from a chemical supply company.\n**Sr:** Source strontium from a specialty chemical supplier.",
      "steps": [
        "**As:** Purchase from a chemical supplier or online platform (ensure purity).",
        "**Mn:** Obtain from a metal supplier, such as a local hardware store or online.",
        "**Na:** Buy sodium metal from a chemical supply company.",
        "**Sr:** Source strontium from a specialty chemical supplier."
      ]
    },
    "preparation": {
      "steps": [
        "1. Weigh out 187.5 g of arsenic and place it in a clean glass beaker.",
        "2. Weigh 187.5 g of manganese and add it to the beaker.",
        "3. Measure 7.5 g of sodium and carefully add to the beaker (handle sodium with caution, as it reacts with moisture).",
        "4. Add 300 g of strontium to the beaker.",
        "5. Mix the ingredients thoroughly using a glass rod until uniform consistency is achieved."
      ],
      "raw_text": "1. Weigh out 187.5 g of arsenic and place it in a clean glass beaker.\n2. Weigh 187.5 g of manganese and add it to the beaker.\n3. Measure 7.5 g of sodium and carefully add to the beaker (handle sodium with caution, as it reacts with moisture).\n4. Add 300 g of strontium to the beaker.\n5. Mix the ingredients thoroughly using a glass rod until uniform consistency is achieved."
    },
    "heating": {
      "temperature_celsius": 800,
      "duration_hours": 2,
      "steps": [
        "1. Transfer the mixed material into a crucible.",
        "2. Place the crucible in a furnace.",
        "3. Heat the furnace to 800째C (1472째F) for 2 hours to ensure complete melting and mixing of the components."
      ],
      "raw_text": "1. Transfer the mixed material into a crucible.\n2. Place the crucible in a furnace.\n3. Heat the furnace to 800째C (1472째F) for 2 hours to ensure complete melting and mixing of the components."
    },
    "cooling": {
      "cooling_time_hours": 6,
      "method": "natural",
      "steps": [
        "1. After heating, turn off the furnace and allow it to cool down to room temperature naturally (approximately 4-6 hours).",
        "2. Do not open the furnace until it reaches a safe temperature to avoid thermal shock to the material."
      ],
      "raw_text": "1. After heating, turn off the furnace and allow it to cool down to room temperature naturally (approximately 4-6 hours).\n2. Do not open the furnace until it reaches a safe temperature to avoid thermal shock to the material."
    },
    "post_processing": {
      "steps": [
        "1. Once cooled, remove the solid sample from the crucible.",
        "2. Use a fine-grit sandpaper to smooth any rough edges.",
        "3. Optionally, apply a sealant to protect the surface if intended for display or storage."
      ],
      "raw_text": "1. Once cooled, remove the solid sample from the crucible.\n2. Use a fine-grit sandpaper to smooth any rough edges.\n3. Optionally, apply a sealant to protect the surface if intended for display or storage."
    }
  },
  "properties": {
    "structure": {
      "nsites": 25,
      "volume": 4765787.0,
      "density": 5826.0,
      "crystal_system": "tetragonal",
      "space_group": "I4/m",
      "space_group_number": 87,
      "point_group": "4/m",
      "dimensionality": "intercalated ion"
    },
    "energetics": {
      "corrected_energy": -1589684.0,
      "formation_energy_per_atom": -5071.0,
      "decomposition_energy_per_atom": -146.0,
      "decomposition_energy_all": 0.0,
      "decomposition_energy_relative": -7.0,
      "decomposition_energy_mp": -146.0,
      "decomposition_energy_mp_oqmd": -21.0
    },
    "electronic": {
      "bandgap": 0.0029,
      "bandgap_type": "semiconductor"
    },
    "metadata": {
      "material_id": "7437bb3763",
      "is_train": true
    }
  },
  "metadata": {
    "source": "Acadia Nanoforge Database",
    "data_version": "1.0",
    "created_at": "2025-10-30T15:13:47.537167Z",
    "mcp_version": "2024-11-05",
    "access_patterns": [
      "materials/As10Mn10Na1Sr4.json",
      "material://As10Mn10Na1Sr4"
    ]
  }
}