{
  "id": "Bi1Sc12Si15Tm8",
  "uri": "material://Bi1Sc12Si15Tm8",
  "composition": {
    "formula": "Bi1Sc12Si15Tm8",
    "elements": {
      "Bi": 1,
      "Sc": 12,
      "Si": 15,
      "Tm": 8
    },
    "reduced_formula": "Tm8Sc12Si15Bi",
    "element_list": [
      "Si",
      "Sc",
      "Tm",
      "Bi"
    ]
  },
  "recipe": {
    "materials": {
      "list": [],
      "raw_text": "Bismuth (Bi): 10.5 g \n Scandium (Sc): 7.5 g \n Silicon (Si): 15 g \n Thulium (Tm): 9 g"
    },
    "sourcing": {
      "instructions": "Bismuth: Available at chemical supply stores or online vendors specializing in metals. \n Scandium: Rare; can be sourced from specialty metal suppliers or online platforms. \n Silicon: Commonly found at electronics or hardware stores. \n Thulium: Obtainable from chemical suppliers or online specialized metal vendors.",
      "steps": [
        "Bismuth: Available at chemical supply stores or online vendors specializing in metals.",
        "Scandium: Rare; can be sourced from specialty metal suppliers or online platforms.",
        "Silicon: Commonly found at electronics or hardware stores.",
        "Thulium: Obtainable from chemical suppliers or online specialized metal vendors."
      ]
    },
    "preparation": {
      "steps": [
        "1. Weigh each ingredient using an analytical balance for precision.",
        "2. Place all ingredients in a clean, dry mixing container.",
        "3. Use a spatula to mix the powders thoroughly until a homogeneous mixture is achieved."
      ],
      "raw_text": "1. Weigh each ingredient using an analytical balance for precision. \n 2. Place all ingredients in a clean, dry mixing container. \n 3. Use a spatula to mix the powders thoroughly until a homogeneous mixture is achieved."
    },
    "heating": {
      "temperature_celsius": 1200,
      "duration_hours": 2,
      "steps": [
        "1. Transfer the mixture to a high-temperature crucible.",
        "2. Heat the crucible in a furnace to 1200°C.",
        "3. Maintain this temperature for 2 hours to ensure complete melting and reaction of the materials."
      ],
      "raw_text": "1. Transfer the mixture to a high-temperature crucible. \n 2. Heat the crucible in a furnace to 1200°C. \n 3. Maintain this temperature for 2 hours to ensure complete melting and reaction of the materials."
    },
    "cooling": {
      "cooling_time_hours": 6,
      "method": "natural",
      "steps": [
        "1. Turn off the furnace and allow it to cool down to room temperature gradually (approx. 4-6 hours).",
        "2. Once the furnace is at room temperature, remove the crucible carefully using heat-resistant gloves."
      ],
      "raw_text": "1. Turn off the furnace and allow it to cool down to room temperature gradually (approx. 4-6 hours). \n 2. Once the furnace is at room temperature, remove the crucible carefully using heat-resistant gloves."
    },
    "post_processing": {
      "steps": [
        "1. Allow the solidified sample to cool for an additional 1 hour at room temperature.",
        "2. Use sandpaper to smooth the surface of the sample, starting with a coarse grit and finishing with a fine grit.",
        "3. Optionally, apply a sealant to protect the surface of the material."
      ],
      "raw_text": "1. Allow the solidified sample to cool for an additional 1 hour at room temperature. \n 2. Use sandpaper to smooth the surface of the sample, starting with a coarse grit and finishing with a fine grit. \n 3. Optionally, apply a sealant to protect the surface of the material."
    }
  },
  "properties": {
    "structure": {
      "nsites": 36,
      "volume": 7340593.0,
      "density": 57033.0,
      "crystal_system": "triclinic",
      "space_group": "P1",
      "space_group_number": 1,
      "point_group": "1",
      "dimensionality": "3D"
    },
    "energetics": {
      "corrected_energy": -2259137.0,
      "formation_energy_per_atom": -8013.0,
      "decomposition_energy_per_atom": -146.0,
      "decomposition_energy_all": 0.0,
      "decomposition_energy_relative": -137.0,
      "decomposition_energy_mp": -141.0,
      "decomposition_energy_mp_oqmd": -139.0
    },
    "electronic": {
      "bandgap": 0.0018,
      "bandgap_type": "semiconductor"
    },
    "metadata": {
      "material_id": "a06c4d7c7b",
      "is_train": true
    }
  },
  "metadata": {
    "source": "Acadia Nanoforge Database",
    "data_version": "1.0",
    "created_at": "2025-10-30T15:14:46.542276Z",
    "mcp_version": "2024-11-05",
    "access_patterns": [
      "materials/Bi1Sc12Si15Tm8.json",
      "material://Bi1Sc12Si15Tm8"
    ]
  }
}