{
  "id": "Bi8Er13Ga4Tb7",
  "uri": "material://Bi8Er13Ga4Tb7",
  "composition": {
    "formula": "Bi8Er13Ga4Tb7",
    "elements": {
      "Bi": 8,
      "Er": 13,
      "Ga": 4,
      "Tb": 7
    },
    "reduced_formula": "Tb7Er13(GaBi2)4",
    "element_list": [
      "Ga",
      "Tb",
      "Er",
      "Bi"
    ]
  },
  "recipe": {
    "materials": {
      "list": [],
      "raw_text": "Bismuth (Bi): 80.00 g \n Erbium (Er): 12.50 g \n Gallium (Ga): 24.00 g \n Terbium (Tb): 35.00 g"
    },
    "sourcing": {
      "instructions": "Bismuth: Available from metal supply shops or online metal retailers. \n Erbium: Obtain from specialized rare earth metal suppliers or online chemical suppliers. \n Gallium: Available from electronic supply stores or online. \n Terbium: Sourced from rare earth suppliers or online chemical retailers.",
      "steps": [
        "Bismuth: Available from metal supply shops or online metal retailers.",
        "Erbium: Obtain from specialized rare earth metal suppliers or online chemical suppliers.",
        "Gallium: Available from electronic supply stores or online.",
        "Terbium: Sourced from rare earth suppliers or online chemical retailers."
      ]
    },
    "preparation": {
      "steps": [
        "1. Weigh out 80.00 g of Bismuth using a precision scale.",
        "2. Weigh 12.50 g of Erbium.",
        "3. Weigh 24.00 g of Gallium.",
        "4. Weigh 35.00 g of Terbium.",
        "5. Combine all weighed ingredients in a clean, dry ceramic or glass container.",
        "6. Mix thoroughly with a clean stainless steel spatula until uniform."
      ],
      "raw_text": "1. Weigh out 80.00 g of Bismuth using a precision scale. \n 2. Weigh 12.50 g of Erbium. \n 3. Weigh 24.00 g of Gallium. \n 4. Weigh 35.00 g of Terbium. \n 5. Combine all weighed ingredients in a clean, dry ceramic or glass container. \n 6. Mix thoroughly with a clean stainless steel spatula until uniform."
    },
    "heating": {
      "temperature_celsius": 900,
      "duration_hours": 2,
      "steps": [
        "1. Transfer the mixed powder to a high-temperature crucible.",
        "2. Place the crucible in a furnace or high-temperature oven.",
        "3. Heat to a temperature of 900째C (1652째F) and maintain for 2 hours to ensure complete melting and alloying of the components."
      ],
      "raw_text": "1. Transfer the mixed powder to a high-temperature crucible. \n 2. Place the crucible in a furnace or high-temperature oven. \n 3. Heat to a temperature of 900째C (1652째F) and maintain for 2 hours to ensure complete melting and alloying of the components."
    },
    "cooling": {
      "cooling_time_hours": 2,
      "method": "natural",
      "steps": [
        "1. After the heating duration, turn off the furnace and allow it to cool down naturally to room temperature (approximately 1-2 hours).",
        "2. Once the furnace is cool, carefully remove the crucible using heat-resistant gloves."
      ],
      "raw_text": "1. After the heating duration, turn off the furnace and allow it to cool down naturally to room temperature (approximately 1-2 hours). \n 2. Once the furnace is cool, carefully remove the crucible using heat-resistant gloves."
    },
    "post_processing": {
      "steps": [
        "1. Allow the solidified sample to cool further at room temperature for an additional hour.",
        "2. Once fully cooled, remove the sample from the crucible.",
        "3. If necessary, use a file or sandpaper to smooth any rough edges or surfaces on the sample.",
        "4. Optionally, seal the sample with a clear acrylic or epoxy coating for added protection against oxidation."
      ],
      "raw_text": "1. Allow the solidified sample to cool further at room temperature for an additional hour. \n 2. Once fully cooled, remove the sample from the crucible. \n 3. If necessary, use a file or sandpaper to smooth any rough edges or surfaces on the sample. \n 4. Optionally, seal the sample with a clear acrylic or epoxy coating for added protection against oxidation."
    }
  },
  "properties": {
    "structure": {
      "nsites": 32,
      "volume": 901141.0,
      "density": 96513.0,
      "crystal_system": "monoclinic",
      "space_group": "Pm",
      "space_group_number": 6,
      "point_group": "m",
      "dimensionality": "3D"
    },
    "energetics": {
      "corrected_energy": -1554555.0,
      "formation_energy_per_atom": -6376.0,
      "decomposition_energy_per_atom": -17.0,
      "decomposition_energy_all": 2.0,
      "decomposition_energy_relative": 2.0,
      "decomposition_energy_mp": -17.0,
      "decomposition_energy_mp_oqmd": -166.0
    },
    "electronic": {
      "bandgap": 0.0014,
      "bandgap_type": "semiconductor"
    },
    "metadata": {
      "material_id": "04cb190d89",
      "is_train": true
    }
  },
  "metadata": {
    "source": "Acadia Nanoforge Database",
    "data_version": "1.0",
    "created_at": "2025-10-30T15:11:21.341370Z",
    "mcp_version": "2024-11-05",
    "access_patterns": [
      "materials/Bi8Er13Ga4Tb7.json",
      "material://Bi8Er13Ga4Tb7"
    ]
  }
}