{
  "id": "C7Sm3Tb2W2",
  "uri": "material://C7Sm3Tb2W2",
  "composition": {
    "formula": "C7Sm3Tb2W2",
    "elements": {
      "C": 7,
      "Sm": 3,
      "Tb": 2,
      "W": 2
    },
    "reduced_formula": "Tb2Sm3W2C7",
    "element_list": [
      "C",
      "Sm",
      "Tb",
      "W"
    ]
  },
  "recipe": {
    "materials": {
      "list": [
        {
          "element": "C",
          "amount": 4.5,
          "unit": "g"
        },
        {
          "element": "Sm",
          "amount": 2.1,
          "unit": "g"
        },
        {
          "element": "Tb",
          "amount": 1.8,
          "unit": "g"
        },
        {
          "element": "W",
          "amount": 3.6,
          "unit": "g"
        }
      ],
      "raw_text": "C: 4.5 g (Carbon) \n Sm: 2.1 g (Samarium) \n Tb: 1.8 g (Terbium) \n W: 3.6 g (Tungsten)"
    },
    "sourcing": {
      "instructions": "C: Available from chemical supply stores or online retailers. \n Sm: Obtain from rare earth materials suppliers. \n Tb: Available from specialized metal suppliers. \n W: Obtain from industrial metal suppliers or online.",
      "steps": [
        "C: Available from chemical supply stores or online retailers.",
        "Sm: Obtain from rare earth materials suppliers.",
        "Tb: Available from specialized metal suppliers.",
        "W: Obtain from industrial metal suppliers or online."
      ]
    },
    "preparation": {
      "steps": [
        "1. Measure each ingredient using a precise scale.",
        "2. In a clean mixing container, combine 4.5 g of Carbon, 2.1 g of Samarium, 1.8 g of Terbium, and 3.6 g of Tungsten.",
        "3. Mix thoroughly using a spatula or electronic mixer until a homogeneous powder is achieved."
      ],
      "raw_text": "1. Measure each ingredient using a precise scale. \n 2. In a clean mixing container, combine 4.5 g of Carbon, 2.1 g of Samarium, 1.8 g of Terbium, and 3.6 g of Tungsten. \n 3. Mix thoroughly using a spatula or electronic mixer until a homogeneous powder is achieved."
    },
    "heating": {
      "temperature_celsius": 1200,
      "duration_hours": 2,
      "steps": [
        "1. Transfer the mixture into a crucible suitable for high-temperature applications.",
        "2. Heat the crucible in a furnace to a temperature of 1200째C.",
        "3. Maintain this temperature for a duration of 2 hours to ensure complete reaction and formation of the compound."
      ],
      "raw_text": "1. Transfer the mixture into a crucible suitable for high-temperature applications. \n 2. Heat the crucible in a furnace to a temperature of 1200째C. \n 3. Maintain this temperature for a duration of 2 hours to ensure complete reaction and formation of the compound."
    },
    "cooling": {
      "method": "natural",
      "steps": [
        "1. After heating, turn off the furnace and allow the crucible to cool gradually to room temperature (approximately 25째C).",
        "2. Once cooled, carefully remove the crucible from the furnace."
      ],
      "raw_text": "1. After heating, turn off the furnace and allow the crucible to cool gradually to room temperature (approximately 25째C). \n 2. Once cooled, carefully remove the crucible from the furnace."
    },
    "post_processing": {
      "steps": [
        "1. Remove the solidified material from the crucible.",
        "2. Use sandpaper to smooth any rough edges and achieve desired dimensions.",
        "3. Optionally, apply a sealant or coating to protect the surface, if required.",
        "4. Allow any sealant to cure as per manufacturer's instructions."
      ],
      "raw_text": "1. Remove the solidified material from the crucible. \n 2. Use sandpaper to smooth any rough edges and achieve desired dimensions. \n 3. Optionally, apply a sealant or coating to protect the surface, if required. \n 4. Allow any sealant to cure as per manufacturer's instructions."
    }
  },
  "properties": {
    "structure": {
      "nsites": 14,
      "volume": 21325.0,
      "density": 95053.0,
      "crystal_system": "monoclinic",
      "space_group": "P2/m",
      "space_group_number": 10,
      "point_group": "2/m",
      "dimensionality": "3D"
    },
    "energetics": {
      "corrected_energy": -1179358.0,
      "formation_energy_per_atom": -2863.0,
      "decomposition_energy_per_atom": -515.0,
      "decomposition_energy_all": 8.0,
      "decomposition_energy_relative": 8.0,
      "decomposition_energy_mp": -515.0,
      "decomposition_energy_mp_oqmd": -214.0
    },
    "electronic": {
      "bandgap": null,
      "bandgap_type": "semiconductor"
    },
    "metadata": {
      "material_id": "3a43294a39",
      "is_train": true
    }
  },
  "metadata": {
    "source": "Acadia Nanoforge Database",
    "data_version": "1.0",
    "created_at": "2025-10-30T15:12:32.352006Z",
    "mcp_version": "2024-11-05",
    "access_patterns": [
      "materials/C7Sm3Tb2W2.json",
      "material://C7Sm3Tb2W2"
    ]
  }
}