{
  "id": "Cd3Ga2In1Nd3",
  "uri": "material://Cd3Ga2In1Nd3",
  "composition": {
    "formula": "Cd3Ga2In1Nd3",
    "elements": {
      "Cd": 3,
      "Ga": 2,
      "In": 1,
      "Nd": 3
    },
    "reduced_formula": "Nd3Cd3InGa2",
    "element_list": [
      "Ga",
      "Cd",
      "In",
      "Nd"
    ]
  },
  "recipe": {
    "materials": {
      "list": [],
      "raw_text": "Cadmium (Cd): 15.0 g \n Gallium (Ga): 6.0 g \n Indium (In): 2.0 g \n Neodymium (Nd): 12.0 g"
    },
    "sourcing": {
      "instructions": "Cadmium: Purchase from a chemical supply company or online specialty metal suppliers. \n Gallium: Available from industrial metal suppliers, online marketplaces, or specialty electronics suppliers. \n Indium: Obtain from metal suppliers or online chemical retailers. \n Neodymium: Source from rare earth metal suppliers or online metal retailers.",
      "steps": [
        "Cadmium: Purchase from a chemical supply company or online specialty metal suppliers.",
        "Gallium: Available from industrial metal suppliers, online marketplaces, or specialty electronics suppliers.",
        "Indium: Obtain from metal suppliers or online chemical retailers.",
        "Neodymium: Source from rare earth metal suppliers or online metal retailers."
      ]
    },
    "preparation": {
      "steps": [
        "1. Weigh each ingredient accurately using a digital scale.",
        "2. In a clean, dry beaker, combine 15.0 g of cadmium, 6.0 g of gallium, 2.0 g of indium, and 12.0 g of neodymium.",
        "3. Stir the mixture with a non-reactive stirrer until all components are evenly distributed."
      ],
      "raw_text": "1. Weigh each ingredient accurately using a digital scale. \n 2. In a clean, dry beaker, combine 15.0 g of cadmium, 6.0 g of gallium, 2.0 g of indium, and 12.0 g of neodymium. \n 3. Stir the mixture with a non-reactive stirrer until all components are evenly distributed."
    },
    "heating": {
      "temperature_celsius": 800,
      "duration_hours": 2,
      "heating_rate_celsius_per_min": 10,
      "steps": [
        "1. Transfer the mixture to a suitable crucible.",
        "2. Place the crucible in a high-temperature furnace.",
        "3. Heat gradually to 800°C at a rate of 10°C/min.",
        "4. Maintain this temperature for 2 hours to ensure complete alloying."
      ],
      "raw_text": "1. Transfer the mixture to a suitable crucible. \n 2. Place the crucible in a high-temperature furnace. \n 3. Heat gradually to 800°C at a rate of 10°C/min. \n 4. Maintain this temperature for 2 hours to ensure complete alloying."
    },
    "cooling": {
      "method": "natural",
      "steps": [
        "1. After the heating duration, turn off the furnace and allow it to cool naturally to room temperature (approximately 25°C).",
        "2. Do not remove the crucible until the temperature has stabilized to prevent thermal shock."
      ],
      "raw_text": "1. After the heating duration, turn off the furnace and allow it to cool naturally to room temperature (approximately 25°C). \n 2. Do not remove the crucible until the temperature has stabilized to prevent thermal shock."
    },
    "post_processing": {
      "steps": [
        "1. Once cooled, remove the solid sample from the crucible.",
        "2. Inspect the sample for any surface imperfections.",
        "3. If necessary, use fine-grit sandpaper to smooth any rough edges.",
        "4. Optionally, apply a protective sealant suitable for metal alloys to enhance durability."
      ],
      "raw_text": "1. Once cooled, remove the solid sample from the crucible. \n 2. Inspect the sample for any surface imperfections. \n 3. If necessary, use fine-grit sandpaper to smooth any rough edges. \n 4. Optionally, apply a protective sealant suitable for metal alloys to enhance durability."
    }
  },
  "properties": {
    "structure": {
      "nsites": 9,
      "volume": 2259592.0,
      "density": 75269.0,
      "crystal_system": "hexagonal",
      "space_group": "P-62m",
      "space_group_number": 189,
      "point_group": "-6m2",
      "dimensionality": "3D"
    },
    "energetics": {
      "corrected_energy": -30361.0,
      "formation_energy_per_atom": -4978.0,
      "decomposition_energy_per_atom": -91.0,
      "decomposition_energy_all": 1.0,
      "decomposition_energy_relative": 1.0,
      "decomposition_energy_mp": -91.0,
      "decomposition_energy_mp_oqmd": -5.0
    },
    "electronic": {
      "bandgap": 0.0194,
      "bandgap_type": "semiconductor"
    },
    "metadata": {
      "material_id": "16df0262e9",
      "is_train": true
    }
  },
  "metadata": {
    "source": "Acadia Nanoforge Database",
    "data_version": "1.0",
    "created_at": "2025-10-30T15:11:45.622066Z",
    "mcp_version": "2024-11-05",
    "access_patterns": [
      "materials/Cd3Ga2In1Nd3.json",
      "material://Cd3Ga2In1Nd3"
    ]
  }
}