{
  "id": "Co4Nd4Y12Zn4",
  "uri": "material://Co4Nd4Y12Zn4",
  "composition": {
    "formula": "Co4Nd4Y12Zn4",
    "elements": {
      "Co": 4,
      "Nd": 4,
      "Y": 12,
      "Zn": 4
    },
    "reduced_formula": "NdY3ZnCo",
    "element_list": [
      "Co",
      "Zn",
      "Y",
      "Nd"
    ]
  },
  "recipe": {
    "materials": {
      "list": [],
      "raw_text": "Cobalt (Co): 24.00 g \n Neodymium (Nd): 42.40 g \n Yttrium (Y): 12.00 g \n Zinc (Zn): 19.20 g"
    },
    "sourcing": {
      "instructions": "Cobalt: Purchase from a chemical supply company or online retailers specializing in metal powders. \n Neodymium: Obtain from specialized metal suppliers or online platforms like eBay or Amazon. \n Yttrium: Available from chemical suppliers. \n Zinc: Found at hardware stores or chemical suppliers.",
      "steps": [
        "Cobalt: Purchase from a chemical supply company or online retailers specializing in metal powders.",
        "Neodymium: Obtain from specialized metal suppliers or online platforms like eBay or Amazon.",
        "Yttrium: Available from chemical suppliers.",
        "Zinc: Found at hardware stores or chemical suppliers."
      ]
    },
    "preparation": {
      "steps": [
        "1. Measure each ingredient accurately using a digital scale.",
        "2. In a clean, dry container, combine the measured cobalt, neodymium, yttrium, and zinc powders.",
        "3. Use a mortar and pestle to grind the mixture thoroughly for 10-15 minutes until uniform."
      ],
      "raw_text": "1. Measure each ingredient accurately using a digital scale.\n 2. In a clean, dry container, combine the measured cobalt, neodymium, yttrium, and zinc powders.\n 3. Use a mortar and pestle to grind the mixture thoroughly for 10-15 minutes until uniform."
    },
    "heating": {
      "temperature_celsius": 1200,
      "duration_hours": 2,
      "steps": [
        "1. Transfer the mixture to a crucible suitable for high temperatures.",
        "2. Place the crucible in a furnace set to 1200째C (2192째F).",
        "3. Heat for 2 hours to ensure complete reaction and alloy formation."
      ],
      "raw_text": "1. Transfer the mixture to a crucible suitable for high temperatures.\n 2. Place the crucible in a furnace set to 1200째C (2192째F).\n 3. Heat for 2 hours to ensure complete reaction and alloy formation."
    },
    "cooling": {
      "cooling_time_hours": 6,
      "method": "natural",
      "steps": [
        "1. After heating, turn off the furnace and allow it to cool to room temperature naturally.",
        "2. Do not open the furnace door until it has cooled completely, which takes approximately 4-6 hours."
      ],
      "raw_text": "1. After heating, turn off the furnace and allow it to cool to room temperature naturally.\n 2. Do not open the furnace door until it has cooled completely, which takes approximately 4-6 hours."
    },
    "post_processing": {
      "steps": [
        "1. Once cooled, remove the solid sample from the crucible.",
        "2. Inspect for any rough edges and use sandpaper (grit 120-220) to smooth the surface.",
        "3. Optionally, apply a sealant or protective coating to enhance durability and appearance."
      ],
      "raw_text": "1. Once cooled, remove the solid sample from the crucible.\n 2. Inspect for any rough edges and use sandpaper (grit 120-220) to smooth the surface.\n 3. Optionally, apply a sealant or protective coating to enhance durability and appearance."
    }
  },
  "properties": {
    "structure": {
      "nsites": 24,
      "volume": 6040825.0,
      "density": 58859.0,
      "crystal_system": "cubic",
      "space_group": "F-43m",
      "space_group_number": 216,
      "point_group": "-43m",
      "dimensionality": "3D"
    },
    "energetics": {
      "corrected_energy": -1351872.0,
      "formation_energy_per_atom": -2102.0,
      "decomposition_energy_per_atom": -7.0,
      "decomposition_energy_all": 0.0,
      "decomposition_energy_relative": -2.0,
      "decomposition_energy_mp": -7.0,
      "decomposition_energy_mp_oqmd": -52.0
    },
    "electronic": {
      "bandgap": 0.0072,
      "bandgap_type": "semiconductor"
    },
    "metadata": {
      "material_id": "6fc3368282",
      "is_train": true
    }
  },
  "metadata": {
    "source": "Acadia Nanoforge Database",
    "data_version": "1.0",
    "created_at": "2025-10-30T15:13:41.727513Z",
    "mcp_version": "2024-11-05",
    "access_patterns": [
      "materials/Co4Nd4Y12Zn4.json",
      "material://Co4Nd4Y12Zn4"
    ]
  }
}