{
  "id": "La2Mo4O14Sm1Tm1",
  "uri": "material://La2Mo4O14Sm1Tm1",
  "composition": {
    "formula": "La2Mo4O14Sm1Tm1",
    "elements": {
      "La": 2,
      "Mo": 4,
      "O": 14,
      "Sm": 1,
      "Tm": 1
    },
    "reduced_formula": "La2SmTm(Mo2O7)2",
    "element_list": [
      "O",
      "Mo",
      "La",
      "Sm",
      "Tm"
    ]
  },
  "recipe": {
    "materials": {
      "list": [],
      "raw_text": "- La2O3: 36.43 g \n - MoO3: 81.58 g \n - Sm2O3: 17.62 g \n - Tm2O3: 3.93 g \n - Binder (e.g., PVA): 15 g \n - Solvent (e.g., Ethanol): 30 mL"
    },
    "sourcing": {
      "instructions": "- La2O3: Available from chemical supply companies or online platforms like Sigma-Aldrich. \n - MoO3: Can be sourced from specialty chemical suppliers. \n - Sm2O3 and Tm2O3: Obtainable from rare earth material suppliers. \n - PVA and Ethanol: Commonly available at hardware stores or online.",
      "steps": [
        "- La2O3: Available from chemical supply companies or online platforms like Sigma-Aldrich.",
        "- MoO3: Can be sourced from specialty chemical suppliers.",
        "- Sm2O3 and Tm2O3: Obtainable from rare earth material suppliers.",
        "- PVA and Ethanol: Commonly available at hardware stores or online."
      ]
    },
    "preparation": {
      "steps": [
        "1. Weigh out La2O3, MoO3, Sm2O3, and Tm2O3 with a precision scale.",
        "2. In a clean, dry container, combine La2O3, MoO3, Sm2O3, and Tm2O3.",
        "3. Slowly add PVA binder to the dry blend while continuously mixing.",
        "4. Gradually add Ethanol to achieve a paste-like consistency.",
        "5. Mix thoroughly until uniform."
      ],
      "raw_text": "1. Weigh out La2O3, MoO3, Sm2O3, and Tm2O3 with a precision scale. \n 2. In a clean, dry container, combine La2O3, MoO3, Sm2O3, and Tm2O3. \n 3. Slowly add PVA binder to the dry blend while continuously mixing. \n 4. Gradually add Ethanol to achieve a paste-like consistency. \n 5. Mix thoroughly until uniform."
    },
    "heating": {
      "temperature_celsius": 900,
      "duration_hours": 4,
      "steps": [
        "1. Preheat the furnace to 900°C.",
        "2. Place the mixture in a suitable crucible.",
        "3. Heat the mixture for 4 hours to ensure complete reaction and formation of La2Mo4O14Sm1Tm1."
      ],
      "raw_text": "1. Preheat the furnace to 900°C. \n 2. Place the mixture in a suitable crucible. \n 3. Heat the mixture for 4 hours to ensure complete reaction and formation of La2Mo4O14Sm1Tm1."
    },
    "cooling": {
      "cooling_time_hours": 2,
      "method": "natural",
      "steps": [
        "1. Turn off the furnace and allow it to cool naturally to room temperature (approximately 2 hours).",
        "2. Avoid rapid cooling to prevent cracking."
      ],
      "raw_text": "1. Turn off the furnace and allow it to cool naturally to room temperature (approximately 2 hours). \n 2. Avoid rapid cooling to prevent cracking."
    },
    "post_processing": {
      "steps": [
        "1. Once cooled, remove the sample from the crucible.",
        "2. Sand the edges and surfaces with fine-grit sandpaper to achieve a smooth finish.",
        "3. Optionally, apply a sealant if the material is to be exposed to moisture or handling."
      ],
      "raw_text": "1. Once cooled, remove the sample from the crucible. \n 2. Sand the edges and surfaces with fine-grit sandpaper to achieve a smooth finish. \n 3. Optionally, apply a sealant if the material is to be exposed to moisture or handling."
    }
  },
  "properties": {
    "structure": {
      "nsites": 22,
      "volume": 2967383.0,
      "density": 67423.0,
      "crystal_system": "monoclinic",
      "space_group": "C2/m",
      "space_group_number": 12,
      "point_group": "2/m",
      "dimensionality": "3D"
    },
    "energetics": {
      "corrected_energy": -1965192.0,
      "formation_energy_per_atom": -29454.0,
      "decomposition_energy_per_atom": -367.0,
      "decomposition_energy_all": 0.0,
      "decomposition_energy_relative": -31.0,
      "decomposition_energy_mp": -373.0,
      "decomposition_energy_mp_oqmd": -207.0
    },
    "electronic": {
      "bandgap": 1.2717,
      "bandgap_type": "semiconductor"
    },
    "metadata": {
      "material_id": "68ac6ab940",
      "is_train": true
    }
  },
  "metadata": {
    "source": "Acadia Nanoforge Database",
    "data_version": "1.0",
    "created_at": "2025-10-30T15:13:32.635355Z",
    "mcp_version": "2024-11-05",
    "access_patterns": [
      "materials/La2Mo4O14Sm1Tm1.json",
      "material://La2Mo4O14Sm1Tm1"
    ]
  }
}