{
  "id": "Ni20Si4Zr2",
  "uri": "material://Ni20Si4Zr2",
  "composition": {
    "formula": "Ni20Si4Zr2",
    "elements": {
      "Ni": 20,
      "Si": 4,
      "Zr": 2
    },
    "reduced_formula": "Zr(SiNi5)2",
    "element_list": [
      "Si",
      "Ni",
      "Zr"
    ]
  },
  "recipe": {
    "materials": {
      "list": [],
      "raw_text": "Nickel (Ni): 200 g \n Silicon (Si): 40 g \n Zirconium (Zr): 20 g"
    },
    "sourcing": {
      "instructions": "Nickel: Purchase from a metal supplier or online marketplace (e.g., Amazon, eBay). \n Silicon: Obtain from chemical supply companies or online. \n Zirconium: Sourced from specialized metal suppliers or online.",
      "steps": [
        "Nickel: Purchase from a metal supplier or online marketplace (e.g., Amazon, eBay).",
        "Silicon: Obtain from chemical supply companies or online.",
        "Zirconium: Sourced from specialized metal suppliers or online."
      ]
    },
    "preparation": {
      "steps": [
        "1. Weigh out 200 g of nickel powder, 40 g of silicon powder, and 20 g of zirconium powder using a precision scale.",
        "2. Combine the powders in a clean, dry mixing container.",
        "3. Use a mechanical mixer or mortar and pestle to mix thoroughly for at least 10 minutes to ensure a homogenous blend."
      ],
      "raw_text": "1. Weigh out 200 g of nickel powder, 40 g of silicon powder, and 20 g of zirconium powder using a precision scale. \n 2. Combine the powders in a clean, dry mixing container. \n 3. Use a mechanical mixer or mortar and pestle to mix thoroughly for at least 10 minutes to ensure a homogenous blend."
    },
    "heating": {
      "temperature_celsius": 1200,
      "duration_hours": 2,
      "steps": [
        "1. Place the mixed powders into a suitable crucible.",
        "2. Heat the crucible in a high-temperature furnace.",
        "3. Set the furnace temperature to 1200°C and maintain this temperature for 2 hours to allow for complete alloying."
      ],
      "raw_text": "1. Place the mixed powders into a suitable crucible. \n 2. Heat the crucible in a high-temperature furnace. \n 3. Set the furnace temperature to 1200°C and maintain this temperature for 2 hours to allow for complete alloying."
    },
    "cooling": {
      "cooling_time_hours": 2,
      "method": "natural",
      "steps": [
        "1. After heating, turn off the furnace and allow it to cool naturally to room temperature (approximately 1-2 hours).",
        "2. Avoid rapid cooling to prevent cracking or warping of the alloy."
      ],
      "raw_text": "1. After heating, turn off the furnace and allow it to cool naturally to room temperature (approximately 1-2 hours). \n 2. Avoid rapid cooling to prevent cracking or warping of the alloy."
    },
    "post_processing": {
      "steps": [
        "1. Once cooled, remove the solid sample from the crucible.",
        "2. Use fine-grit sandpaper to polish the surface, ensuring a smooth finish.",
        "3. Optionally, apply a protective sealant to enhance durability and corrosion resistance."
      ],
      "raw_text": "1. Once cooled, remove the solid sample from the crucible. \n 2. Use fine-grit sandpaper to polish the surface, ensuring a smooth finish. \n 3. Optionally, apply a protective sealant to enhance durability and corrosion resistance."
    }
  },
  "properties": {
    "structure": {
      "nsites": 26,
      "volume": 3048724.0,
      "density": 79993.0,
      "crystal_system": "tetragonal",
      "space_group": "P4/nmm",
      "space_group_number": 129,
      "point_group": "4/mmm",
      "dimensionality": "3D"
    },
    "energetics": {
      "corrected_energy": -165689.0,
      "formation_energy_per_atom": -4342.0,
      "decomposition_energy_per_atom": -41.0,
      "decomposition_energy_all": 0.0,
      "decomposition_energy_relative": -141.0,
      "decomposition_energy_mp": -15.0,
      "decomposition_energy_mp_oqmd": -141.0
    },
    "electronic": {
      "bandgap": 0.0022,
      "bandgap_type": "semiconductor"
    },
    "metadata": {
      "material_id": "633c06f51d",
      "is_train": true
    }
  },
  "metadata": {
    "source": "Acadia Nanoforge Database",
    "data_version": "1.0",
    "created_at": "2025-10-30T15:13:25.775846Z",
    "mcp_version": "2024-11-05",
    "access_patterns": [
      "materials/Ni20Si4Zr2.json",
      "material://Ni20Si4Zr2"
    ]
  }
}