{
  "id": "O8Pr1Se1Tc1",
  "uri": "material://O8Pr1Se1Tc1",
  "composition": {
    "formula": "O8Pr1Se1Tc1",
    "elements": {
      "O": 8,
      "Pr": 1,
      "Se": 1,
      "Tc": 1
    },
    "reduced_formula": "PrTcSeO8",
    "element_list": [
      "O",
      "Se",
      "Tc",
      "Pr"
    ]
  },
  "recipe": {
    "materials": {
      "list": [],
      "raw_text": "- Barium Oxide (BaO): 90.0 g  \n - Potassium Carbonate (K2CO3): 21.0 g  \n - Manganese Oxide (MnO): 176.0 g  \n - Phosphorus Pentoxide (P2O5): 160.0 g"
    },
    "sourcing": {
      "instructions": "- Barium Oxide: Specialty chemical suppliers or online platforms like Amazon or chemical supply websites.  \n - Potassium Carbonate: Garden supply stores or chemical suppliers.  \n - Manganese Oxide: Chemical suppliers or metal supply stores.  \n - Phosphorus Pentoxide: Chemical supply companies or online specialty stores.",
      "steps": [
        "- Barium Oxide: Specialty chemical suppliers or online platforms like Amazon or chemical supply websites.",
        "- Potassium Carbonate: Garden supply stores or chemical suppliers.",
        "- Manganese Oxide: Chemical suppliers or metal supply stores.",
        "- Phosphorus Pentoxide: Chemical supply companies or online specialty stores."
      ]
    },
    "preparation": {
      "steps": [
        "1. Measure out 90.0 g of Barium Oxide and place it in a clean mixing container.",
        "2. Add 21.0 g of Potassium Carbonate to the container.",
        "3. Gradually add 176.0 g of Manganese Oxide while mixing to ensure even distribution.",
        "4. Finally, incorporate 160.0 g of Phosphorus Pentoxide into the mixture, ensuring no clumps remain and that all powders are homogeneous."
      ],
      "raw_text": "1. Measure out 90.0 g of Barium Oxide and place it in a clean mixing container.  \n 2. Add 21.0 g of Potassium Carbonate to the container.  \n 3. Gradually add 176.0 g of Manganese Oxide while mixing to ensure even distribution.  \n 4. Finally, incorporate 160.0 g of Phosphorus Pentoxide into the mixture, ensuring no clumps remain and that all powders are homogeneous."
    },
    "heating": {
      "temperature_celsius": 900,
      "duration_hours": 2,
      "steps": [
        "1. Transfer the mixed powder into a heat-resistant crucible.",
        "2. Place the crucible in a furnace and heat to 900°C (1652°F).",
        "3. Maintain this temperature for 2 hours to ensure complete reaction and fusion of the materials."
      ],
      "raw_text": "1. Transfer the mixed powder into a heat-resistant crucible.  \n 2. Place the crucible in a furnace and heat to 900°C (1652°F).  \n 3. Maintain this temperature for 2 hours to ensure complete reaction and fusion of the materials."
    },
    "cooling": {
      "cooling_time_hours": 8,
      "method": "natural",
      "steps": [
        "1. After heating, turn off the furnace and allow it to cool naturally to room temperature (approximately 25°C or 77°F).",
        "2. This cooling process should take about 6-8 hours."
      ],
      "raw_text": "1. After heating, turn off the furnace and allow it to cool naturally to room temperature (approximately 25°C or 77°F).  \n 2. This cooling process should take about 6-8 hours."
    },
    "post_processing": {
      "steps": [
        "1. Remove the solidified material from the crucible once cooled.",
        "2. Use a diamond grinding tool to smooth the edges and surfaces to achieve the desired dimensions (3 inches x 2 inches x 7 inches).",
        "3. Optionally, seal the surface with a clear epoxy resin to enhance durability and appearance."
      ],
      "raw_text": "1. Remove the solidified material from the crucible once cooled.  \n 2. Use a diamond grinding tool to smooth the edges and surfaces to achieve the desired dimensions (3 inches x 2 inches x 7 inches).  \n 3. Optionally, seal the surface with a clear epoxy resin to enhance durability and appearance."
    }
  },
  "properties": {
    "structure": {
      "nsites": 11,
      "volume": 2141083.0,
      "density": 34579.0,
      "crystal_system": "trigonal",
      "space_group": "P3",
      "space_group_number": 143,
      "point_group": "3",
      "dimensionality": "2D"
    },
    "energetics": {
      "corrected_energy": -815741.0,
      "formation_energy_per_atom": -2123.0,
      "decomposition_energy_per_atom": -1319.0,
      "decomposition_energy_all": 0.0,
      "decomposition_energy_relative": -323.0,
      "decomposition_energy_mp": -1326.0,
      "decomposition_energy_mp_oqmd": -1278.0
    },
    "electronic": {
      "bandgap": 2.5105,
      "bandgap_type": "semiconductor"
    },
    "metadata": {
      "material_id": "cfef023a27",
      "is_train": true
    }
  },
  "metadata": {
    "source": "Acadia Nanoforge Database",
    "data_version": "1.0",
    "created_at": "2025-10-30T15:15:21.242699Z",
    "mcp_version": "2024-11-05",
    "access_patterns": [
      "materials/O8Pr1Se1Tc1.json",
      "material://O8Pr1Se1Tc1"
    ]
  }
}